mlcommons_box_singularity/__init__.py
mlcommons_box_singularity/__main__.py
mlcommons_box_singularity/mlbox-singularity.yaml
mlcommons_box_singularity/singularity_run.py
mlcommons_box_singularity/tests/__init__.py
mlcommons_box_singularity/tests/test_mlcommons_box_singularity_cli.py
mlcommons_box_singularity-0.2.3.dist-info/METADATA
mlcommons_box_singularity-0.2.3.dist-info/WHEEL
mlcommons_box_singularity-0.2.3.dist-info/entry_points.txt
mlcommons_box_singularity-0.2.3.dist-info/top_level.txt
mlcommons_box_singularity-0.2.3.dist-info/RECORD
